resources/code/majority16.v
// Write a Verilog module to implement a 16-bit majority function using behavioral description. The module will take as input a 16-bit data, Data and provide a single-bit output, Out, indicating the logic state of the most number of input bits, i.e. if at least 9 out of 16 input signals are at logic 1, the logic state of Out will be 1; otherwise Out will remain at  logic 0. The template of the function will be as follows :

//        module majority16 (Out, Data);

// Hint: May use Verilog loop constructs for the design.

module majority16 (
    Out, Data
);
output Out;
input [0:15] Data;

//to count the 1s 
  reg [0:4] count;
  integer i;

//if count >8 ,Out =1;
assign Out = count > 4'b1000 ? 1 : 0;//taken 5 becaus

always @(Data) begin//whenever Data value changes then come to this block
    count=4'b0;
    for (i=0;i<16 ;i=i+1 ) begin
        if (Data[i]==1'b1) begin
            count=count+1;
        end
    end
end
endmodule


//test bench for given module

module top;
//
reg [0:15] Data;
wire Out;
//instantiate 
majority16 dut(Out,Data);

//behavioural block
initial begin
    $dumpfile("majority16.vcd");
    $dumpvars(0,top);
    #5 Data=16'b1001000101111101;
    #5 Data=16'b0101010101010101;
    #5 Data=16'b1111001101010101;
    #5 Data=16'b0010111111011110;
    #5 Data=16'b1111111111111111;
    #5 Data=16'b1111010110101111;
    #5 Data=16'b1111100000110000;
    #5 Data=16'b0;
end


endmodule

majority16.vcd
$date
	Fri Dec 22 14:16:31 2023
$end
$version
	Icarus Verilog
$end
$timescale
	1s
$end
$scope module top $end
$var wire 1 ! Out $end
$var reg 16 " Data [0:15] $end
$scope module dut $end
$var wire 16 # Data [0:15] $end
$var wire 1 ! Out $end
$var reg 5 $ count [0:4] $end
$var integer 32 % i [31:0] $end
$upscope $end
$upscope $end
$enddefinitions $end
#0
$dumpvars
bx %
bx $
bx #
bx "
x!
$end
#5
1!
b10000 %
b1001 $
b1001000101111101 "
b1001000101111101 #
#10
0!
b10000 %
b1000 $
b101010101010101 "
b101010101010101 #
#15
1!
b10000 %
b1010 $
b1111001101010101 "
b1111001101010101 #
#20
b10000 %
b1011 $
b10111111011110 "
b10111111011110 #
#25
b10000 %
b10000 $
b1111111111111111 "
b1111111111111111 #
#30
b10000 %
b1100 $
b1111010110101111 "
b1111010110101111 #
#35
0!
b10000 %
b111 $
b1111100000110000 "
b1111100000110000 #
#40
b10000 %
b0 $
b0 "
b0 #
