resources/code/cyclic_lamp.v

/*

*/

module cyclic_lamp (
    light,clk
);
output reg [2:0] light;
input clk;

parameter s0=0,s1=1,s2=2 ;
parameter RED =3'b001,GREEN=3'b010,YELLOW=3'b100;

reg [0:1] state;

always @(posedge clk ) begin
    case (state)
        s0:begin////       in red state
            light<=GREEN;
            state<=s1;
        end 
        s1:begin
            light<=YELLOW;
            state<=s2;
        end
        s2:begin
            light<=RED;
            state<=s0;
        end
        default:begin
            light<=RED;
            state<=s0;
        end
    endcase
end
    
endmodule

///test bench

module tb_cyclic_lamp;

wire [2:0] light;
reg clk;

parameter time_period=10;
cyclic_lamp dut(light,clk);

always #(time_period/2) clk=~clk;

initial begin
    clk=0;
    #100 $finish;
end

initial begin
    $dumpfile("cyclic_lamp.vcd");
    $dumpvars(0,tb_cyclic_lamp);
    $monitor($time ," RGY=%b",light);
end

endmodule

resources/code/cyclic_lamp.vcd
$date
	Tue Jan 09 17:32:18 2024
$end
$version
	Icarus Verilog
$end
$timescale
	1s
$end
$scope module tb_cyclic_lamp $end
$var wire 3 ! light [2:0] $end
$var reg 1 " clk $end
$scope module dut $end
$var wire 1 # clk $end
$var reg 3 $ light [2:0] $end
$var reg 2 % state [0:1] $end
$upscope $end
$upscope $end
$enddefinitions $end
#0
$dumpvars
bx %
bx $
0#
0"
bx !
$end
#5
b0 %
b1 $
b1 !
1"
1#
#10
0"
0#
#15
b1 %
b10 $
b10 !
1"
1#
#20
0"
0#
#25
b10 %
b100 $
b100 !
1"
1#
#30
0"
0#
#35
b0 %
b1 $
b1 !
1"
1#
#40
0"
0#
#45
b1 %
b10 $
b10 !
1"
1#
#50
0"
0#
#55
b10 %
b100 $
b100 !
1"
1#
#60
0"
0#
#65
b0 %
b1 $
b1 !
1"
1#
#70
0"
0#
#75
b1 %
b10 $
b10 !
1"
1#
#80
0"
0#
#85
b10 %
b100 $
b100 !
1"
1#
#90
0"
0#
#95
b0 %
b1 $
b1 !
1"
1#
